merlon-1.3.1.dist-info/METADATA
merlon-1.3.1.dist-info/WHEEL
merlon/__init__.py
merlon/merlon.abi3.so
merlon-1.3.1.dist-info/RECORD
