Metadata-Version: 2.1
Name: merlon
Version: 1.3.1
Summary: Mod package manager for the Paper Mario (N64) decompilation
Author: Alex Bates <alex@nanaian.town>
Author-email: Alex Bates <alex@nanaian.town>
License: MPL-2.0
Project-URL: Source Code, https://github.com/nanaian/merlon
